triglav/__init__.py
triglav/triglav.py
triglav-1.0.7.dist-info/METADATA
triglav-1.0.7.dist-info/WHEEL
triglav-1.0.7.dist-info/licenses/LICENSE
triglav-1.0.7.dist-info/RECORD
