Metadata-Version: 2.3
Name: triglav
Version: 1.0.7
Summary: Triglav: Iterative Refinement and Selection of Stable Features Using Shapley Values
Project-URL: Homepage, https://github.com/jrudar/Triglav
Project-URL: Repository, https://github.com/jrudar/Triglav.git
Project-URL: Bug Tracker, https://github.com/jrudar/Triglav/issues
Author: Peter Kruczkiewicz, G. Brian Golding, Oliver Lung
Author-email: Josip Rudar <joe.rudar@inspection.gc.ca>, Mehrdad Hajibabaei <mhajibab@uoguelph.ca>
License: MIT License
License-File: LICENSE
Keywords: ecology,feature selection,multivariate statistics,stability selection
Classifier: Development Status :: 5 - Production/Stable
Classifier: Intended Audience :: Science/Research
Classifier: License :: OSI Approved :: MIT License
Classifier: Natural Language :: English
Classifier: Operating System :: OS Independent
Classifier: Programming Language :: Python :: 3
Classifier: Programming Language :: Python :: 3 :: Only
Classifier: Programming Language :: Python :: 3.10
Classifier: Programming Language :: Python :: 3.11
Classifier: Programming Language :: Python :: 3.12
Requires-Python: >=3.10
Requires-Dist: imbalanced-learn>=0.10.1
Requires-Dist: joblib>=1.1.0
Requires-Dist: matplotlib>=3.4.3
Requires-Dist: numpy>=1.26
Requires-Dist: sage-importance>=0.0.5
Requires-Dist: scikit-learn>=1.0.1
Requires-Dist: scipy>=1.7.3
Requires-Dist: shap>=0.40.0
Requires-Dist: statsmodels>=0.12.0
Provides-Extra: dev
Requires-Dist: black; extra == 'dev'
Requires-Dist: mypy; extra == 'dev'
Requires-Dist: ruff; extra == 'dev'
Requires-Dist: twine; extra == 'dev'
Provides-Extra: test
Requires-Dist: pytest; extra == 'test'
Requires-Dist: pytest-cov; extra == 'test'
